expkit/__init__.py
expkit/eval.py
expkit/exp.py
expkit/ops.py
expkit/pexp.py
expkit/setup.py
expkit/storage.py
expkit/storage/__init__.py
expkit/storage/base.py
expkit/storage/cache.py
expkit/storage/disk.py
expkit/storage/memory.py
expkit/storage/mongo.py
expkit/storage/zip.py
tests/__init__.py
tests/test_exp.py
tests/test_pexp.py
tests/test_setup.py
expkit_core-1.0.5.dist-info/LICENSE
expkit_core-1.0.5.dist-info/METADATA
expkit_core-1.0.5.dist-info/WHEEL
expkit_core-1.0.5.dist-info/top_level.txt
expkit_core-1.0.5.dist-info/RECORD
