Metadata-Version: 2.1
Name: expkit-core
Version: 1.0.5
Summary: Package for managing research experiments text results.
Home-page: https://github.com/goncalorafaria/expkit-core
Author: Goncalo Faria
Author-email: gfaria@cs.washington.edu
Classifier: Programming Language :: Python :: 3
Classifier: License :: OSI Approved :: MIT License
Classifier: Operating System :: OS Independent
Requires-Python: >=3.6.0
License-File: LICENSE
